agviz/__init__.py
agviz/drawing.py
agviz/graph_modifiers.py
agviz/make_graph.py
agviz-1.0.1.dist-info/licenses/LICENSE
agviz-1.0.1.dist-info/METADATA
agviz-1.0.1.dist-info/WHEEL
agviz-1.0.1.dist-info/top_level.txt
agviz-1.0.1.dist-info/RECORD
