Metadata-Version: 2.4
Name: agviz
Version: 1.0.1
Summary: AutoGrad Visualizer (agviz): Visualize dependencies between states/parameters in autograd tree.
Home-page: https://github.com/meeree/agviz
Author: James Hazelden
Requires-Python: >=3.2
License-File: LICENSE
Requires-Dist: graphviz
Requires-Dist: networkx
Dynamic: author
Dynamic: description
Dynamic: description-content-type
Dynamic: home-page
Dynamic: license-file
Dynamic: requires-dist
Dynamic: requires-python
Dynamic: summary
